emoji_cli/__init__.py
emoji_cli/emoji_cli.py
emoji_cli/emoji_const.py
emoji_cli/emoji_dict.py
emoji_cli/emoji_util.py
emoji_cli/db/emoji.data
test/__init__.py
test/test_emoji_cli.py
test/test_emoji_const.py
test/test_emoji_dict.py
test/test_emoji_util.py
emoji_cli-0.0.1.dist-info/LICENSE
emoji_cli-0.0.1.dist-info/METADATA
emoji_cli-0.0.1.dist-info/WHEEL
emoji_cli-0.0.1.dist-info/entry_points.txt
emoji_cli-0.0.1.dist-info/top_level.txt
emoji_cli-0.0.1.dist-info/RECORD
