Metadata-Version: 2.1
Name: emoji-cli
Version: 0.0.1
Summary: A emoji clis tool with python
Home-page: https://github.com/houbb/emoji-cli
Author: houbb
Author-email: houbinbin.echo@gmail.com
License: UNKNOWN
Keywords: tool,emoji,clis,shell,emoji-cli,表情emoji命令行工具
Platform: UNKNOWN
Classifier: Programming Language :: Python :: 3
Classifier: License :: OSI Approved :: Apache Software License
Classifier: Operating System :: OS Independent
Requires-Dist: fire
